website_diff-0.1.0.dist-info/METADATA
website_diff-0.1.0.dist-info/WHEEL
website_diff-0.1.0.dist-info/entry_points.txt
website_diff-0.1.0.dist-info/licenses/LICENSE
website_diff/target/__init__.py
website_diff/target/image.py
website_diff/render/altair.py
website_diff/render/__init__.py
website_diff/render/prerender.py
website_diff/render/plotly.py
website_diff/__init__.py
website_diff/page.py
website_diff/cli.py
website_diff/static/website_diff.js
website_diff/static/website_diff.css
website_diff/crawler.py
website_diff/htmldiff.cpython-311-darwin.so
website_diff-0.1.0.dist-info/RECORD
