Metadata-Version: 2.3
Name: website_diff
Version: 0.1.0
Classifier: Programming Language :: Rust
Classifier: Programming Language :: Python :: Implementation :: CPython
Classifier: Programming Language :: Python :: Implementation :: PyPy
Requires-Dist: click
Requires-Dist: loguru
Requires-Dist: beautifulsoup4
Requires-Dist: pillow
Requires-Dist: numpy
Requires-Dist: vl-convert-python
Requires-Dist: selenium
Requires-Dist: cairosvg
Requires-Dist: maturin
License-File: LICENSE
Summary: A simple tool for producing navigable, highlighted diffs of rendered HTML websites
Author-email: Trevor Campbell <trevor.d.campbell@gmail.com>
Requires-Python: >=3.9
